{
    "AX": {
        "error": 0.007317747560767553, 
        "fit": "average", 
        "value": 0.04342736035715733
    }, 
    "CDD": {
        "error": 2.1138057666820127e-05, 
        "fit": "average", 
        "value": 0.0001926589481008715
    }, 
    "H1": {
        "error": 0.006179634839653075, 
        "fit": "average", 
        "value": -0.02207420073218589
    }, 
    "H2": {
        "error": 0.006646672119196299, 
        "fit": "average", 
        "value": 0.0803177002288735
    }, 
    "L1": {
        "error": 0.005615873913923835, 
        "fit": "average", 
        "value": 0.1412917969434678
    }, 
    "L2": {
        "error": 0.0025079813294927953, 
        "fit": "average", 
        "value": 0.009959669008574932
    }
}